{
  "profile": {
    "username": "sweta", 
    "_id": "4cdcb85a-c073-4022-a354-808696f22942", 
    "experience": 119
  }, 
  "occupied_planets": {
    "007:001:04": {
      "shelio": 5, 
      "graphene": {
        "amount": 48, 
        "reserved": 45
      }, 
      "mines": {
        "G101": {
          "mined": 1314, 
          "_id": "G101", 
          "type": "GRAPHENE", 
          "mining_plant": {
            "building_level": 9, 
            "workers": 6, 
            "building_id": "GMP101"
          }
        }, 
        "G102": {
          "mined": 661, 
          "_id": "G102", 
          "type": "GRAPHENE", 
          "mining_plant": {
            "building_level": 0, 
            "workers": 0, 
            "building_id": null
          }
        }, 
        "G103": {
          "mined": 207, 
          "_id": "G103", 
          "type": "GRAPHENE", 
          "mining_plant": {
            "building_level": 2, 
            "workers": 13, 
            "building_id": "GMP103"
          }
        }, 
        "G104": {
          "mined": 830, 
          "_id": "G104", 
          "type": "GRAPHENE", 
          "mining_plant": {
            "building_level": 0, 
            "workers": 0, 
            "building_id": null
          }
        }, 
        "W101": {
          "mined": 1223, 
          "_id": "W101", 
          "type": "WATER", 
          "mining_plant": {
            "building_level": 0, 
            "workers": 0, 
            "building_id": null
          }
        }, 
        "W102": {
          "mined": 200, 
          "_id": "W102", 
          "type": "WATER", 
          "mining_plant": {
            "building_level": 1, 
            "workers": 12, 
            "building_id": "WMP102"
          }
        }, 
        "W103": {
          "mined": 619, 
          "_id": "W103", 
          "type": "WATER", 
          "mining_plant": {
            "building_level": 3, 
            "workers": 9, 
            "building_id": "WMP103"
          }
        }, 
        "W104": {
          "mined": 663, 
          "_id": "W104", 
          "type": "WATER", 
          "mining_plant": {
            "building_level": 0, 
            "workers": 0, 
            "building_id": null
          }
        }, 
        "W105": {
          "mined": 44, 
          "_id": "W105", 
          "type": "WATER", 
          "mining_plant": {
            "building_level": 2, 
            "workers": 13, 
            "building_id": "WMP105"
          }
        }, 
        "W106": {
          "mined": 1270, 
          "_id": "W106", 
          "type": "WATER", 
          "mining_plant": {
            "building_level": 6, 
            "workers": 8, 
            "building_id": "WMP106"
          }
        }, 
        "W107": {
          "mined": 702, 
          "_id": "W107", 
          "type": "WATER", 
          "mining_plant": {
            "building_level": 9, 
            "workers": 6, 
            "building_id": "WMP107"
          }
        }, 
        "W108": {
          "mined": 788, 
          "_id": "W108", 
          "type": "WATER", 
          "mining_plant": {
            "building_level": 0, 
            "workers": 0, 
            "building_id": null
          }
        }
      }, 
      "water": {
        "amount": 30, 
        "reserved": 19
      }, 
      "home": true, 
      "position": {
        "sector": 1, 
        "planet": 4, 
        "_id": "007:001:04", 
        "system": 7
      }, 
      "population": {
        "soldiers": {
          "idle": 2, 
          "total": 16
        }, 
        "unemployed": 7, 
        "generation_rate": 1, 
        "workers": {
          "idle": 2, 
          "total": 17
        }
      }
    }
  }
}